pulsefig/__config__.py
pulsefig/__init__.py
pulsefig/annotate.py
pulsefig/element.py
pulsefig/forms.py
pulsefig/line.py
pulsefig/styles.py
pulsefig/utils.py
pulsefig/variables.py
pulsefig-0.2.0.dist-info/LICENCE
pulsefig-0.2.0.dist-info/METADATA
pulsefig-0.2.0.dist-info/WHEEL
pulsefig-0.2.0.dist-info/top_level.txt
pulsefig-0.2.0.dist-info/RECORD
