Metadata-Version: 2.1
Name: pulsefig
Version: 0.2.0
Summary: Plot pulse sequences.
Home-page: https://github.com/kyrylo-gr/pulsefig
Author: kyrylo.gr
Author-email: git@kyrylo.gr
Classifier: Programming Language :: Python :: 3
Classifier: Operating System :: OS Independent
Requires-Python: >=3.8
License-File: LICENCE
Requires-Dist: numpy
Requires-Dist: matplotlib
Requires-Dist: uastyle
